cpyuda.cp311-win_amd64.pyd
pyuda/_client.py
pyuda/_data.py
pyuda/_dim.py
pyuda/_json.py
pyuda/_signal.py
pyuda/_string.py
pyuda/_structured.py
pyuda/_tree.py
pyuda/_utils.py
pyuda/_version.py
pyuda/_video.py
pyuda/__init__.py
pyuda/cpyuda/cpyuda.cpp
pyuda-2.9.1.data/platlib/msvcp140-a4c2229bdc2a2a630acdc095b4d86008.dll
pyuda-2.9.1.data/platlib/uda_client-f953b233cd6a82d102d2c608dafc2c38.dll
pyuda-2.9.1.dist-info/DELVEWHEEL
pyuda-2.9.1.dist-info/METADATA
pyuda-2.9.1.dist-info/RECORD
pyuda-2.9.1.dist-info/top_level.txt
pyuda-2.9.1.dist-info/WHEEL
uda/setup.py
uda/__init__.py
